tgcaller/__init__.py
tgcaller/cli.py
tgcaller/client.py
tgcaller/exceptions.py
tgcaller/handlers/__init__.py
tgcaller/handlers/event_handler.py
tgcaller/methods/__init__.py
tgcaller/methods/call_methods.py
tgcaller/methods/stream_methods.py
tgcaller/plugins/__init__.py
tgcaller/plugins/base_plugin.py
tgcaller/plugins/plugin_manager.py
tgcaller/types/__init__.py
tgcaller/types/audio_config.py
tgcaller/types/call_update.py
tgcaller/types/media_stream.py
tgcaller/types/video_config.py
tgcaller/utils/__init__.py
tgcaller/utils/logger.py
tgcaller/utils/media_utils.py
tgcaller-1.0.2.dist-info/licenses/LICENSE
tgcaller-1.0.2.dist-info/METADATA
tgcaller-1.0.2.dist-info/WHEEL
tgcaller-1.0.2.dist-info/entry_points.txt
tgcaller-1.0.2.dist-info/top_level.txt
tgcaller-1.0.2.dist-info/RECORD
