Metadata-Version: 2.4
Name: tgcaller
Version: 1.0.2
Summary: Modern, fast, and reliable Telegram group calls library
Author-email: TgCaller Team <team@tgcaller.dev>
Maintainer-email: TgCaller Team <team@tgcaller.dev>
License: MIT
Project-URL: Homepage, https://github.com/tgcaller/tgcaller
Project-URL: Documentation, https://tgcaller.readthedocs.io
Project-URL: Repository, https://github.com/tgcaller/tgcaller
Project-URL: Issues, https://github.com/tgcaller/tgcaller/issues
Project-URL: Community, https://t.me/tgcaller
Keywords: telegram,calls,voip,streaming,audio,video,pytgcalls,alternative,modern,fast,reliable
Classifier: Development Status :: 5 - Production/Stable
Classifier: Intended Audience :: Developers
Classifier: License :: OSI Approved :: MIT License
Classifier: Operating System :: OS Independent
Classifier: Programming Language :: Python :: 3
Classifier: Programming Language :: Python :: 3.8
Classifier: Programming Language :: Python :: 3.9
Classifier: Programming Language :: Python :: 3.10
Classifier: Programming Language :: Python :: 3.11
Classifier: Programming Language :: Python :: 3.12
Classifier: Topic :: Communications
Classifier: Topic :: Internet
Classifier: Topic :: Multimedia :: Sound/Audio
Classifier: Topic :: Multimedia :: Video
Classifier: Topic :: Software Development :: Libraries :: Python Modules
Classifier: Typing :: Typed
Requires-Python: >=3.8
License-File: LICENSE
Requires-Dist: pyrogram>=2.0.106
Requires-Dist: aiortc>=1.6.0
Requires-Dist: aiofiles>=23.1.0
Requires-Dist: aiohttp>=3.8.4
Requires-Dist: ffmpeg-python>=0.2.0
Requires-Dist: numpy>=1.24.0
Requires-Dist: pyaudio>=0.2.11
Requires-Dist: soundfile>=0.12.1
Requires-Dist: yt-dlp>=2023.6.22
Requires-Dist: requests>=2.31.0
Requires-Dist: asyncio-throttle>=1.0.2
Requires-Dist: uvloop>=0.17.0; sys_platform != "win32"
Requires-Dist: loguru>=0.7.0
Requires-Dist: psutil>=5.9.5
Requires-Dist: pydantic>=1.10.8
Requires-Dist: python-dotenv>=1.0.0
Provides-Extra: dev
Requires-Dist: pytest>=7.0.0; extra == "dev"
Requires-Dist: pytest-asyncio>=0.21.0; extra == "dev"
Requires-Dist: black>=22.0.0; extra == "dev"
Requires-Dist: isort>=5.10.0; extra == "dev"
Requires-Dist: flake8>=4.0.0; extra == "dev"
Requires-Dist: mypy>=0.950; extra == "dev"
Provides-Extra: video
Requires-Dist: opencv-python>=4.7.0; extra == "video"
Requires-Dist: imageio>=2.28.0; extra == "video"
Dynamic: license-file
